{"uniED8B": "\u5f20", "uniF5FE": "\u751f", "uniE51D": "\u7ecf", "uniEC8E": "\u58eb", "uniE8AF": "\u6821", "uniF4FC": "\u5218", "uniF310": "\u79d1", "uniEA66": "1", "uniE709": "\u5434", "uniEC44": "\u4e0b", "uniF551": "\u9648", "uniE860": "6", "uniE154": "\u5c4a", "uniE156": "\u4e13", "uniF105": "3", "uniE048": "\u7855", "uniF469": "8", "uniF517": "\u6280", "uniF74E": "\u674e", "uniE512": "\u9ec4", "uniE1DE": "2", "uniE93C": "\u672c", "uniE005": "4", "uniEAE8": "\u5468", "uniF65A": "7", "uniF509": "\u9a8c", "uniE88E": "\u535a", "uniF232": "M", "uniF175": "\u4e2d", "uniEF88": "\u65e0", "uniEE8E": "\u9ad8", "uniE039": "\u5e94", "uniE1E9": "\u8d75", "uniF2E7": "\u4ee5", "uniE344": "0", "uniEBAE": "\u6768", "uniE85D": "A", "uniEB85": "E", "uniE3EB": "5", "uniEC46": "\u5927", "uniF42D": "B", "uniF435": "9", "uniE939": "\u7537", "uniF496": "\u5973", "uniF131": "\u738b"}