{"uniF32D": "\u7855", "uniE894": "9", "uniF451": "\u8d75", "uniF196": "\u7ecf", "uniF02A": "\u9648", "uniF5F4": "\u58eb", "uniEDF5": "\u5218", "uniF0AF": "1", "uniE2A5": "5", "uniF332": "\u4e13", "uniE2F0": "3", "uniEE82": "\u9a8c", "uniF664": "A", "uniEC9B": "\u9ad8", "uniEB8E": "\u79d1", "uniF13C": "\u5e94", "uniF230": "\u5927", "uniE833": "\u5973", "uniE716": "4", "uniE8A7": "\u5468", "uniF26C": "\u751f", "uniE925": "0", "uniE8BD": "\u6280", "uniE8F5": "6", "uniF3DD": "\u9ec4", "uniE5DC": "\u535a", "uniE82C": "\u7537", "uniEC02": "\u672c", "uniF172": "\u4ee5", "uniEC74": "7", "uniEFA6": "M", "uniF8E8": "\u6821", "uniE5DE": "\u4e2d", "uniF0F3": "\u5f20", "uniEC4A": "\u65e0", "uniE884": "B", "uniF626": "\u738b", "uniE229": "E", "uniF15E": "8", "uniECF1": "2", "uniF550": "\u6768", "uniEA63": "\u5434", "uniF764": "\u5c4a", "uniE4C0": "\u4e0b", "uniEB50": "\u674e"}